{
  "results": [
    {
      "products_id": "188626",
      "products_number": 1,
      "products_name": "Nerzugal's Dungeon Master Toolkit",
      "products_image": "/images/8957/188626-thumb140.jpg",
      "whats_new_price": "Pay What You Want",
      "lc_text": "",
      "products_is_pay_what_you_want": "1",
      "products_avg_rating": 0
    },
    {
      "products_id": "186278",
      "products_number": 2,
      "products_name": "Ravenloft Archetypes II: Core Domains Adventurer's Guide",
      "products_image": "/images/8957/186278-thumb140.jpg",
      "whats_new_price": "$3.28",
      "lc_text": "",
      "products_is_pay_what_you_want": "0",
      "products_avg_rating": 0
    },
    {
      "products_id": "170777",
      "products_number": 3,
      "products_name": "Blood Hunter Class",
      "products_image": "/images/8957/170777-thumb140.jpg",
      "whats_new_price": "Pay What You Want",
      "lc_text": "",
      "products_is_pay_what_you_want": "1",
      "products_avg_rating": 0
    },
    {
      "products_id": "170778",
      "products_number": 4,
      "products_name": "Gunslinger Martial Archetype for Fighters",
      "products_image": "/images/8957/170778-thumb140.jpg",
      "whats_new_price": "Pay What You Want",
      "lc_text": "",
      "products_is_pay_what_you_want": "1",
      "products_avg_rating": 0
    },
    {
      "products_id": "183630",
      "products_number": 5,
      "products_name": "College of the Maestro - Bard College Option",
      "products_image": "/images/8957/183630-thumb140.jpg",
      "whats_new_price": "Pay What You Want",
      "lc_text": "",
      "products_is_pay_what_you_want": "1",
      "products_avg_rating": 0
    },
    {
      "products_id": "187283",
      "products_number": 6,
      "products_name": "Heroes of the Orient: Player's and DM's Companion",
      "products_image": "/images/8957/187283-thumb140.jpg",
      "whats_new_price": "$9.99",
      "lc_text": "",
      "products_is_pay_what_you_want": "0",
      "products_avg_rating": 0
    },
    {
      "products_id": "175606",
      "products_number": 7,
      "products_name": "Order of the Lycan for Blood Hunters",
      "products_image": "/images/8957/175606-thumb140.jpg",
      "whats_new_price": "Pay What You Want",
      "lc_text": "",
      "products_is_pay_what_you_want": "1",
      "products_avg_rating": 0
    },
    {
      "products_id": "188180",
      "products_number": 8,
      "products_name": "Puzzles Riddles and Traps",
      "products_image": "/images/8957/188180-thumb140.jpg",
      "whats_new_price": "$1.50",
      "lc_text": "",
      "products_is_pay_what_you_want": "0",
      "products_avg_rating": 0
    },
    {
      "products_id": "186455",
      "products_number": 9,
      "products_name": "The Triboar Trilogy - Adventure Pack",
      "products_image": "/images/8957/186455-thumb140.png",
      "whats_new_price": "$3.00",
      "lc_text": "",
      "products_is_pay_what_you_want": "0",
      "products_avg_rating": 0
    },
    {
      "products_id": "176799",
      "products_number": 10,
      "products_name": "Ravenloft Archetypes: Nightmares of Barovia",
      "products_image": "/images/8957/176799-thumb140.jpg",
      "whats_new_price": "$1.70",
      "lc_text": "",
      "products_is_pay_what_you_want": "0",
      "products_avg_rating": 0
    }
  ]
}